{"end_prop_period": null, "object_type": {"id": null, "name": null}, "internal_name": "Gaia16cfg", "type": null, "discoverydate": "2016-12-17 08:57:07", "source_group": {"group_name": "GaiaAlerts", "groupid": "24"}, "dec": "-45:16:11.57", "discoverer": null, "photometry": [{"filters": {"id": "75", "name": "G"}, "obsdate": "2016-12-17 08:57:07", "fluxerr": "0.2", "flux_unit": {"id": "1", "name": "ABMag"}, "flux": "19.33", "limflux": null, "remarks": "", "instrument": {"id": "163", "name": "Gaia-photometric"}, "telescope": {"id": "107", "name": "Gaia"}, "jd": 2457739.8729977, "observer": "Robot", "exptime": "60"}, {"filters": {"id": "75", "name": "G"}, "obsdate": "2016-11-07 16:00:28", "fluxerr": null, "flux_unit": {"id": "1", "name": "ABMag"}, "flux": null, "limflux": "21.5", "remarks": "[Last non detection] ", "instrument": {"id": "163", "name": "Gaia-photometric"}, "telescope": {"id": "107", "name": "Gaia"}, "jd": 2457699.6669907, "observer": "Robot", "exptime": null}], "public": "1", "ra": "21:28:11.10", "isTNS_AT": "1", "objname": "2016jbe", "redshift": null, "discovererid": "35587", "name_prefix": "AT", "sourceid": "2", "discoverymag": "19.33", "hostname": null, "host_redshift": null, "discmagfilter": "75", "name": null}