{"host_redshift": null, "name_prefix": "AT", "photometry": [{"remarks": "", "flux_unit": {"name": "ABMag", "id": "1"}, "exptime": "60", "instrument": {"name": "Gaia-photometric", "id": "163"}, "telescope": {"name": "Gaia", "id": "107"}, "jd": 2457719.7269907, "fluxerr": "0.2", "limflux": null, "obsdate": "2016-11-27 17:26:52", "filters": {"name": "G", "id": "75"}, "flux": "16.36", "observer": "Robot"}, {"remarks": "[Last non detection] ", "flux_unit": {"name": "ABMag", "id": "1"}, "exptime": null, "instrument": {"name": "Gaia-photometric", "id": "163"}, "telescope": {"name": "Gaia", "id": "107"}, "jd": 2457688.5609954, "fluxerr": null, "limflux": "21.5", "obsdate": "2016-10-27 01:27:50", "filters": {"name": "G", "id": "75"}, "flux": null, "observer": "Robot"}], "name": null, "discoverydate": "2016-11-27 17:26:52", "objname": "2016jgo", "internal_name": "Gaia17aac", "object_type": {"name": null, "id": null}, "discoverer": null, "sourceid": "2", "hostname": null, "discmagfilter": "75", "ra": "18:13:07.91", "type": null, "source_group": {"groupid": "24", "group_name": "GaiaAlerts"}, "public": "1", "discovererid": "35587", "isTNS_AT": "1", "end_prop_period": null, "discoverymag": "16.36", "redshift": null, "dec": "+51:25:00.48"}