{"sourceid": "2", "type": null, "dec": "-04:05:55.73", "photometry": [{"fluxerr": null, "jd": 2457659.8709954, "remarks": "", "exptime": "60", "filters": {"id": "50", "name": "R"}, "observer": "iPTF", "flux_unit": {"id": "1", "name": "ABMag"}, "obsdate": "2016-09-28 08:54:14", "instrument": {"id": "103", "name": "CFH12k"}, "telescope": {"id": "1", "name": "P48"}, "flux": "20.1332", "limflux": null}, {"fluxerr": null, "jd": 2454833, "remarks": "[Last non detection] ", "exptime": "60", "filters": {"id": "50", "name": "R"}, "observer": "iPTF", "flux_unit": {"id": "1", "name": "ABMag"}, "obsdate": "2009-01-01 00:00:00", "instrument": {"id": "103", "name": "CFH12k"}, "telescope": {"id": "1", "name": "P48"}, "flux": null, "limflux": "21.5"}, {"fluxerr": "0.15", "jd": 2457657.9009954, "remarks": "", "exptime": "45", "filters": {"id": "26", "name": "w"}, "observer": "Robot", "flux_unit": {"id": "1", "name": "ABMag"}, "obsdate": "2016-09-26 09:37:26", "instrument": {"id": "155", "name": "GPC1"}, "telescope": {"id": "98", "name": "PS1"}, "flux": "20.36", "limflux": "22"}], "discmagfilter": "26", "discoverymag": "20.36", "hostname": null, "redshift": null, "discoverer": null, "name_prefix": "AT", "host_redshift": null, "objname": "2016gqq", "end_prop_period": null, "internal_name": "PS16eme", "name": null, "ra": "00:23:45.82", "discovererid": "35588", "source_group": {"groupid": "4", "group_name": "Pan-STARRS1"}, "object_type": {"id": null, "name": null}, "isTNS_AT": "1", "discoverydate": "2016-09-26 09:37:26", "public": "1"}