{"photometry": [{"telescope": {"name": "Other", "id": "0"}, "flux_unit": {"name": "VegaMag", "id": "3"}, "fluxerr": "0.1", "limflux": "19.2", "remarks": "", "instrument": {"name": "Other", "id": "0"}, "flux": "19", "jd": 2457651.791875, "observer": "KAIT", "obsdate": "2016-09-20 07:00:18", "exptime": "18", "filters": {"name": "Clear", "id": "1"}}, {"telescope": {"name": "Other", "id": "0"}, "flux_unit": {"name": "VegaMag", "id": "3"}, "fluxerr": null, "limflux": "19.1", "remarks": "[Last non detection] ", "instrument": {"name": "Other", "id": "0"}, "flux": null, "jd": 2457650.7960301, "observer": "KAIT", "obsdate": "2016-09-19 07:06:17", "exptime": "18", "filters": {"name": "Clear", "id": "1"}}], "name_prefix": "AT", "discmagfilter": "1", "host_redshift": "0.005084", "discoverymag": "19", "sourceid": "1", "public": "1", "redshift": null, "discovererid": "172", "discoverydate": "2016-09-20 07:00:18", "discoverer": "Zheng", "internal_name": "kait-16bc", "object_type": {"name": null, "id": null}, "ra": "20:57:10.20", "isTNS_AT": "1", "end_prop_period": null, "source_group": {"group_name": "LOSS", "groupid": "8"}, "hostname": "UGC 11651", "dec": "+25:57:52.09", "type": null, "objname": "2016gky", "name": null}