{"redshift": null, "photometry": [{"remarks": "", "filters": {"id": "71", "name": "cyan"}, "fluxerr": "0.01", "flux_unit": {"id": "1", "name": "ABMag"}, "limflux": "19.25", "instrument": {"id": "159", "name": "ACAM1"}, "flux": "15.06", "observer": "Robot", "obsdate": "2016-09-07 05:57:07", "jd": 2457638.7479977, "telescope": {"id": "103", "name": "ATLAS1"}, "exptime": "30"}, {"remarks": "[Last non detection] ", "filters": {"id": "71", "name": "cyan"}, "fluxerr": null, "flux_unit": {"id": "1", "name": "ABMag"}, "limflux": "19.26", "instrument": {"id": "159", "name": "ACAM1"}, "flux": null, "observer": "Robot", "obsdate": "2016-09-07 05:54:14", "jd": 2457638.7459954, "telescope": {"id": "103", "name": "ATLAS1"}, "exptime": "30"}], "discoverydate": "2016-09-07 05:57:07", "discovererid": "35595", "end_prop_period": null, "name_prefix": "AT", "objname": "2016gsg", "ra": "16:28:52.66", "host_redshift": null, "type": null, "discoverymag": "15.06", "object_type": {"id": null, "name": null}, "public": "1", "name": null, "source_group": {"group_name": "ATLAS", "groupid": "18"}, "internal_name": "ATLAS16czp", "hostname": null, "sourceid": "2", "dec": "+05:00:58.95", "discoverer": null, "discmagfilter": "71", "isTNS_AT": "1"}