{"isTNS_AT": "1", "host_redshift": null, "public": "1", "discmagfilter": "75", "photometry": [{"filters": {"name": "i", "id": "23"}, "jd": 2457744.5979977, "instrument": {"name": "GPC1", "id": "155"}, "flux_unit": {"name": "ABMag", "id": "1"}, "remarks": "", "observer": "Robot", "fluxerr": "0.06", "limflux": "20.7", "flux": "18.85", "obsdate": "2016-12-22 14:21:07", "exptime": "45", "telescope": {"name": "PS1", "id": "98"}}, {"filters": {"name": "G", "id": "75"}, "jd": 2457649.8739931, "instrument": {"name": "Gaia-photometric", "id": "163"}, "flux_unit": {"name": "ABMag", "id": "1"}, "remarks": "", "observer": "Robot", "fluxerr": "0.2", "limflux": null, "flux": "19", "obsdate": "2016-09-18 20:58:33", "exptime": "60", "telescope": {"name": "Gaia", "id": "107"}}, {"filters": {"name": "G", "id": "75"}, "jd": 2457565.6019907, "instrument": {"name": "Gaia-photometric", "id": "163"}, "flux_unit": {"name": "ABMag", "id": "1"}, "remarks": "[Last non detection] ", "observer": "Robot", "fluxerr": null, "limflux": "21.5", "flux": null, "obsdate": "2016-06-26 02:26:52", "exptime": null, "telescope": {"name": "Gaia", "id": "107"}}], "internal_name": "Gaia16biw", "discoverymag": "19", "name_prefix": "AT", "discovererid": "35587", "sourceid": "2", "ra": "09:43:24.72", "objname": "2016gjx", "redshift": null, "discoverer": null, "hostname": null, "name": null, "end_prop_period": null, "type": null, "object_type": {"name": null, "id": null}, "discoverydate": "2016-09-18 20:58:33", "source_group": {"groupid": "24", "group_name": "GaiaAlerts"}, "dec": "+40:20:26.27"}