{"public": "1", "photometry": [{"remarks": "[Last non detection] ", "obsdate": "2009-01-01 00:00:00", "exptime": "60", "instrument": {"id": "103", "name": "CFH12k"}, "observer": "iPTF", "jd": 2454833, "flux_unit": {"id": "1", "name": "ABMag"}, "telescope": {"id": "1", "name": "P48"}, "limflux": "21.5", "fluxerr": null, "filters": {"id": "50", "name": "R"}, "flux": null}, {"remarks": "", "obsdate": "2016-10-21 12:11:31", "exptime": "60", "instrument": {"id": "103", "name": "CFH12k"}, "observer": "iPTF", "jd": 2457683.0079977, "flux_unit": {"id": "1", "name": "ABMag"}, "telescope": {"id": "1", "name": "P48"}, "limflux": null, "fluxerr": null, "filters": {"id": "51", "name": "g"}, "flux": "17.748"}, {"remarks": "", "obsdate": "2016-11-20 14:22:33", "exptime": "45", "instrument": {"id": "155", "name": "GPC1"}, "observer": "Robot", "jd": 2457712.5989931, "flux_unit": {"id": "1", "name": "ABMag"}, "telescope": {"id": "98", "name": "PS1"}, "limflux": "20.7", "fluxerr": "0.06", "filters": {"id": "23", "name": "i"}, "flux": "18.2"}, {"remarks": "", "obsdate": "2016-10-07 13:55:12", "exptime": "30", "instrument": {"id": "159", "name": "ACAM1"}, "observer": "Robot", "jd": 2457668.58, "flux_unit": {"id": "1", "name": "ABMag"}, "telescope": {"id": "103", "name": "ATLAS1"}, "limflux": "19.6", "fluxerr": "0.04", "filters": {"id": "71", "name": "cyan"}, "flux": "17.39"}, {"remarks": "[Last non detection] ", "obsdate": "2016-09-25 15:34:33", "exptime": "30", "instrument": {"id": "159", "name": "ACAM1"}, "observer": "Robot", "jd": 2457656.6489931, "flux_unit": {"id": "1", "name": "ABMag"}, "telescope": {"id": "103", "name": "ATLAS1"}, "limflux": "17.3", "fluxerr": null, "filters": {"id": "71", "name": "cyan"}, "flux": null}, {"remarks": "", "obsdate": "2016-10-08 13:07:40", "exptime": "60", "instrument": {"id": "163", "name": "Gaia-photometric"}, "observer": "Robot", "jd": 2457669.5469907, "flux_unit": {"id": "1", "name": "ABMag"}, "telescope": {"id": "107", "name": "Gaia"}, "limflux": null, "fluxerr": "0.2", "filters": {"id": "75", "name": "G"}, "flux": "17.36"}, {"remarks": "[Last non detection] ", "obsdate": "2016-09-09 19:26:24", "exptime": null, "instrument": {"id": "163", "name": "Gaia-photometric"}, "observer": "Robot", "jd": 2457640.81, "flux_unit": {"id": "1", "name": "ABMag"}, "telescope": {"id": "107", "name": "Gaia"}, "limflux": "21.5", "fluxerr": null, "filters": {"id": "75", "name": "G"}, "flux": null}], "isTNS_AT": "1", "object_type": {"name": null, "id": null}, "discoverydate": "2016-10-07 13:55:12", "source_group": {"groupid": "18", "group_name": "ATLAS"}, "discmagfilter": "71", "dec": "+58:41:37.99", "internal_name": "ATLAS16dic", "sourceid": "2", "redshift": null, "ra": "07:52:43.19", "hostname": null, "discoverer": null, "discovererid": "35595", "host_redshift": null, "type": null, "objname": "2016gzs", "discoverymag": "17.39", "end_prop_period": null, "name": null, "name_prefix": "AT"}