{"discovererid": "11756", "host_redshift": null, "source_group": {"groupid": "2", "group_name": "iPTF"}, "internal_name": "iPTF16fik", "redshift": "0.11", "type": "3", "objname": "2016fik", "dec": "+27:43:57.04", "sourceid": "2", "discoverymag": "19.584", "photometry": [{"jd": 2457625.9279977, "filters": {"id": "50", "name": "R"}, "exptime": "60", "observer": "iPTF", "flux_unit": {"id": "1", "name": "ABMag"}, "telescope": {"id": "1", "name": "P48"}, "obsdate": "2016-08-25 10:16:19", "remarks": "", "fluxerr": null, "limflux": null, "flux": "19.584", "instrument": {"id": "103", "name": "CFH12k"}}, {"jd": 2454833, "filters": {"id": "50", "name": "R"}, "exptime": "60", "observer": "iPTF", "flux_unit": {"id": "1", "name": "ABMag"}, "telescope": {"id": "1", "name": "P48"}, "obsdate": "2009-01-01 00:00:00", "remarks": "[Last non detection] ", "fluxerr": null, "limflux": "21.5", "flux": null, "instrument": {"id": "103", "name": "CFH12k"}}], "ra": "23:25:11.91", "isTNS_AT": "1", "hostname": null, "public": "1", "name_prefix": "SN", "end_prop_period": "2016-09-02", "discoverer": null, "discoverydate": "2016-08-25 10:16:19", "object_type": {"name": null, "id": "3"}, "name": "SN Ia", "discmagfilter": "50"}