{"dec": "+12:04:19.40", "host_redshift": null, "name_prefix": "AT", "photometry": [{"instrument": {"id": "103", "name": "CFH12k"}, "flux": null, "flux_unit": {"id": "1", "name": "ABMag"}, "exptime": "60", "jd": 2454833, "filters": {"id": "50", "name": "R"}, "telescope": {"id": "1", "name": "P48"}, "fluxerr": null, "remarks": "[Last non detection] ", "obsdate": "2009-01-01 00:00:00", "limflux": "21.5", "observer": "iPTF"}, {"instrument": {"id": "103", "name": "CFH12k"}, "flux": "18.3411", "flux_unit": {"id": "1", "name": "ABMag"}, "exptime": "60", "jd": 2457625.685, "filters": {"id": "51", "name": "g"}, "telescope": {"id": "1", "name": "P48"}, "fluxerr": null, "remarks": "", "obsdate": "2016-08-25 04:26:24", "limflux": null, "observer": "iPTF"}, {"instrument": {"id": "159", "name": "ACAM1"}, "flux": "18.23", "flux_unit": {"id": "1", "name": "ABMag"}, "exptime": "30", "jd": 2457607.9559954, "filters": {"id": "71", "name": "cyan"}, "telescope": {"id": "103", "name": "ATLAS1"}, "fluxerr": "0.08", "remarks": "", "obsdate": "2016-08-07 10:56:38", "limflux": "19.8", "observer": "Robot"}, {"instrument": {"id": "159", "name": "ACAM1"}, "flux": null, "flux_unit": {"id": "1", "name": "ABMag"}, "exptime": "30", "jd": 2457592.015, "filters": {"id": "72", "name": "orange"}, "telescope": {"id": "103", "name": "ATLAS1"}, "fluxerr": null, "remarks": "[Last non detection] ", "obsdate": "2016-07-22 12:21:36", "limflux": "18.62", "observer": "Robot"}], "ra": "20:37:40.83", "internal_name": "ATLAS16cjc", "type": null, "discoverer": null, "discmagfilter": "71", "name": null, "end_prop_period": null, "objname": "2016ewz", "object_type": {"id": null, "name": null}, "redshift": null, "source_group": {"groupid": "18", "group_name": "ATLAS"}, "hostname": null, "discoverydate": "2016-08-07 10:56:38", "public": "1", "discoverymag": "18.23", "discovererid": "35595", "isTNS_AT": "1", "sourceid": "2"}