{"discovererid": "49", "ra": "02:45:42.87", "object_type": {"name": null, "id": null}, "hostname": null, "sourceid": "1", "host_redshift": null, "end_prop_period": null, "discoverer": "Young", "discmagfilter": "26", "photometry": [{"instrument": {"id": "155", "name": "GPC1"}, "flux_unit": {"id": "1", "name": "ABMag"}, "obsdate": "2016-01-03 06:27:11", "jd": 2457390.7688773, "limflux": null, "flux": "21.2636", "fluxerr": null, "remarks": "", "telescope": {"id": "98", "name": "PS1"}, "exptime": null, "observer": null, "filters": {"id": "26", "name": "w"}}], "objname": "2016ds", "name": null, "internal_name": "PS16dr", "redshift": null, "discoverymag": "21.2636", "source_group": {"group_name": "Pan-STARRS1", "groupid": "4"}, "isTNS_AT": "1", "public": "1", "name_prefix": "AT", "type": null, "dec": "-04:11:41.86", "discoverydate": "2016-01-03 06:27:11"}