{"redshift": null, "host_redshift": null, "objname": "2016ern", "source_group": {"group_name": "GaiaAlerts", "groupid": "24"}, "sourceid": "2", "discoverer": null, "discoverymag": "17.62", "isTNS_AT": "1", "name": null, "dec": "+21:57:31.75", "photometry": [{"flux_unit": {"id": "1", "name": "ABMag"}, "instrument": {"id": "103", "name": "CFH12k"}, "limflux": null, "obsdate": "2016-08-07 07:59:31", "jd": 2457607.8329977, "observer": "iPTF", "flux": "19.397", "fluxerr": null, "exptime": "60", "telescope": {"id": "1", "name": "P48"}, "filters": {"id": "50", "name": "R"}, "remarks": ""}, {"flux_unit": {"id": "1", "name": "ABMag"}, "instrument": {"id": "103", "name": "CFH12k"}, "limflux": "21.5", "obsdate": "2009-01-01 00:00:00", "jd": 2454833, "observer": "iPTF", "flux": null, "fluxerr": null, "exptime": "60", "telescope": {"id": "1", "name": "P48"}, "filters": {"id": "50", "name": "R"}, "remarks": "[Last non detection] "}, {"flux_unit": {"id": "1", "name": "ABMag"}, "instrument": {"id": "163", "name": "Gaia-photometric"}, "limflux": null, "obsdate": "2016-10-16 05:35:31", "jd": 2457677.7329977, "observer": "Robot", "flux": "17.62", "fluxerr": "0.2", "exptime": "60", "telescope": {"id": "107", "name": "Gaia"}, "filters": {"id": "75", "name": "G"}, "remarks": ""}, {"flux_unit": {"id": "1", "name": "ABMag"}, "instrument": {"id": "163", "name": "Gaia-photometric"}, "limflux": "21.5", "obsdate": "2016-10-01 07:10:33", "jd": 2457662.7989931, "observer": "Robot", "flux": null, "fluxerr": null, "exptime": null, "telescope": {"id": "107", "name": "Gaia"}, "filters": {"id": "75", "name": "G"}, "remarks": "[Last non detection] "}], "ra": "21:01:40.44", "public": "1", "discoverydate": "2016-10-16 05:35:31", "type": null, "hostname": null, "end_prop_period": null, "discovererid": "35587", "name_prefix": "AT", "internal_name": "Gaia16bno", "discmagfilter": "75", "object_type": {"id": null, "name": null}}