{"discoverer": null, "dec": "-08:51:02.44", "object_type": {"id": null, "name": null}, "redshift": null, "sourceid": "2", "discoverydate": "2017-01-28 14:28:19", "host_redshift": null, "type": null, "discoverymag": "21.16", "name_prefix": "AT", "hostname": null, "isTNS_AT": "1", "objname": "2017apm", "internal_name": "PS17ayd", "source_group": {"groupid": "4", "group_name": "Pan-STARRS1"}, "photometry": [{"filters": {"id": "26", "name": "w"}, "flux": "21.16", "instrument": {"id": "155", "name": "GPC1"}, "flux_unit": {"id": "1", "name": "ABMag"}, "telescope": {"id": "98", "name": "PS1"}, "obsdate": "2017-01-28 14:28:19", "fluxerr": "0.12", "limflux": "22", "jd": 2457781.6029977, "observer": "Robot", "remarks": "", "exptime": "45"}], "name": null, "public": "1", "end_prop_period": null, "ra": "13:04:09.69", "discmagfilter": "26", "discovererid": "35588"}