{"objname": "2017bze", "isTNS_AT": "1", "type": null, "internal_name": "Gaia17aop", "name": null, "sourceid": "2", "discoverydate": "2017-03-03 05:13:55", "host_redshift": null, "discmagfilter": "75", "discoverer": null, "discovererid": "35587", "object_type": {"name": null, "id": null}, "public": "1", "source_group": {"groupid": "24", "group_name": "GaiaAlerts"}, "ra": "22:10:18.06", "hostname": null, "end_prop_period": null, "discoverymag": "17.86", "name_prefix": "AT", "photometry": [{"flux": "17.86", "fluxerr": "0.2", "limflux": null, "flux_unit": {"name": "ABMag", "id": "1"}, "exptime": "60", "remarks": "", "jd": 2457815.7179977, "filters": {"name": "G", "id": "75"}, "observer": "Robot", "telescope": {"name": "Gaia", "id": "107"}, "obsdate": "2017-03-03 05:13:55", "instrument": {"name": "Gaia-photometric", "id": "163"}}, {"flux": null, "fluxerr": null, "limflux": "21.5", "flux_unit": {"name": "ABMag", "id": "1"}, "exptime": null, "remarks": "[Last non detection] ", "jd": 2457777.0029977, "filters": {"name": "G", "id": "75"}, "observer": "Robot", "telescope": {"name": "Gaia", "id": "107"}, "obsdate": "2017-01-23 12:04:19", "instrument": {"name": "Gaia-photometric", "id": "163"}}], "dec": "+53:08:35.48", "redshift": null}