{
	"dec":"+14:43:41.49",
	"discmagfilter":{
		"family":"Sloan",
		"id":"23",
		"name":"i"
	},
	"discoverer":null,
	"discovererid":"35588",
	"discoverydate":"2017-04-20 14:05:16",
	"discoverymag":"19.54",
	"end_prop_period":null,
	"host_redshift":null,
	"hostname":null,
	"internal_name":"PS17cph",
	"isTNS_AT":"1",
	"name":"2017dle",
	"name_prefix":"AT",
	"object_type":{
		"id":null,
		"name":null
	},
	"objname":"2017dle",
	"photometry":[
		{
			"exptime":"45",
			"filters":{
				"id":"23",
				"name":"i"
			},
			"flux":"19.54",
			"flux_unit":{
				"id":"1",
				"name":"ABMag"
			},
			"fluxerr":"0.07",
			"instrument":{
				"id":"155",
				"name":"GPC1"
			},
			"jd":2457864.0869907,
			"limflux":"20.7",
			"obsdate":"2017-04-20 14:05:16",
			"observer":"Robot",
			"remarks":"",
			"telescope":{
				"id":"98",
				"name":"PS1"
			}
		}
	],
	"public":"1",
	"ra":"15:59:42.03",
	"redshift":null,
	"source_group":{
		"group_name":"Pan-STARRS1",
		"groupid":"4"
	},
	"sourceid":"2",
	"type":null
}