{"public": "1", "photometry": [{"remarks": "", "obsdate": "2017-02-07 16:42:14", "exptime": "60", "instrument": {"id": "163", "name": "Gaia-photometric"}, "observer": "Robot", "jd": 2457791.6959954, "flux_unit": {"id": "1", "name": "ABMag"}, "telescope": {"id": "107", "name": "Gaia"}, "limflux": null, "fluxerr": "0.2", "filters": {"id": "75", "name": "G"}, "flux": "18.84"}, {"remarks": "[Last non detection] ", "obsdate": "2016-12-31 19:32:09", "exptime": null, "instrument": {"id": "163", "name": "Gaia-photometric"}, "observer": "Robot", "jd": 2457753.8139931, "flux_unit": {"id": "1", "name": "ABMag"}, "telescope": {"id": "107", "name": "Gaia"}, "limflux": "21.5", "fluxerr": null, "filters": {"id": "75", "name": "G"}, "flux": null}], "isTNS_AT": "1", "object_type": {"name": null, "id": null}, "discoverydate": "2017-02-07 16:42:14", "source_group": {"groupid": "24", "group_name": "GaiaAlerts"}, "discmagfilter": "75", "dec": "+55:59:37.03", "internal_name": "Gaia17ajj", "sourceid": "2", "redshift": null, "ra": "13:44:39.38", "hostname": null, "discoverer": null, "discovererid": "35587", "host_redshift": null, "type": null, "objname": "2017awl", "discoverymag": "18.84", "end_prop_period": null, "name": null, "name_prefix": "AT"}