{
	"dec":"+40:43:18.39",
	"discmagfilter":{
		"family":"ATLAS",
		"id":"72",
		"name":"orange"
	},
	"discoverer":null,
	"discovererid":"35595",
	"discoverydate":"2018-10-21 09:11:31",
	"discoverymag":"18.691",
	"end_prop_period":null,
	"host_redshift":null,
	"hostname":null,
	"internal_name":"ATLAS18xtq",
	"isTNS_AT":"1",
	"name":"2018hoa",
	"name_prefix":"SN",
	"object_type":{
		"id":"14",
		"name":"SN IIb"
	},
	"objname":"2018hoa",
	"photometry":[
		{
			"exptime":"30",
			"filters":{
				"id":"72",
				"name":"orange"
			},
			"flux":"18.691",
			"flux_unit":{
				"id":"1",
				"name":"ABMag"
			},
			"fluxerr":"0.124",
			"instrument":{
				"id":"159",
				"name":"ACAM1"
			},
			"jd":2458412.8829977,
			"limflux":"19.03",
			"obsdate":"2018-10-21 09:11:31",
			"observer":"Robot",
			"remarks":"",
			"telescope":{
				"id":"103",
				"name":"ATLAS1"
			}
		},
		{
			"exptime":"30",
			"filters":{
				"id":"72",
				"name":"orange"
			},
			"flux":null,
			"flux_unit":{
				"id":"1",
				"name":"ABMag"
			},
			"fluxerr":null,
			"instrument":{
				"id":"159",
				"name":"ACAM1"
			},
			"jd":2458408.935,
			"limflux":"19.55",
			"obsdate":"2018-10-17 10:26:24",
			"observer":"Robot",
			"remarks":"[Last non detection] ",
			"telescope":{
				"id":"103",
				"name":"ATLAS1"
			}
		},
		{
			"exptime":"60",
			"filters":{
				"id":"75",
				"name":"G"
			},
			"flux":"18.21",
			"flux_unit":{
				"id":"1",
				"name":"ABMag"
			},
			"fluxerr":"0.2",
			"instrument":{
				"id":"163",
				"name":"Gaia-photometric"
			},
			"jd":2458425.1359954,
			"limflux":null,
			"obsdate":"2018-11-02 15:15:50",
			"observer":"Robot",
			"remarks":"",
			"telescope":{
				"id":"107",
				"name":"Gaia"
			}
		},
		{
			"exptime":null,
			"filters":{
				"id":"75",
				"name":"G"
			},
			"flux":null,
			"flux_unit":{
				"id":"1",
				"name":"ABMag"
			},
			"fluxerr":null,
			"instrument":{
				"id":"163",
				"name":"Gaia-photometric"
			},
			"jd":2458373.9609954,
			"limflux":"21.5",
			"obsdate":"2018-09-12 11:03:50",
			"observer":"Robot",
			"remarks":"[Last non detection] ",
			"telescope":{
				"id":"107",
				"name":"Gaia"
			}
		},
		{
			"exptime":"30",
			"filters":{
				"id":"110",
				"name":"g"
			},
			"flux":"19.5731",
			"flux_unit":{
				"id":"1",
				"name":"ABMag"
			},
			"fluxerr":"0.203063",
			"instrument":{
				"id":"196",
				"name":"ZTF-Cam"
			},
			"jd":2458441.7495833,
			"limflux":"19.7415",
			"obsdate":"2018-11-19 05:59:23",
			"observer":null,
			"remarks":"",
			"telescope":{
				"id":"1",
				"name":"P48"
			}
		},
		{
			"exptime":"30",
			"filters":{
				"id":"110",
				"name":"g"
			},
			"flux":"19.1701",
			"flux_unit":{
				"id":"1",
				"name":"ABMag"
			},
			"fluxerr":"0.126369",
			"instrument":{
				"id":"196",
				"name":"ZTF-Cam"
			},
			"jd":2458435.7172338,
			"limflux":"20.1051",
			"obsdate":"2018-11-13 05:12:48",
			"observer":null,
			"remarks":"",
			"telescope":{
				"id":"1",
				"name":"P48"
			}
		},
		{
			"exptime":"30",
			"filters":{
				"id":"110",
				"name":"g"
			},
			"flux":"18.7849",
			"flux_unit":{
				"id":"1",
				"name":"ABMag"
			},
			"fluxerr":"0.0868059",
			"instrument":{
				"id":"196",
				"name":"ZTF-Cam"
			},
			"jd":2458429.7199421,
			"limflux":"20.9145",
			"obsdate":"2018-11-07 05:16:42",
			"observer":null,
			"remarks":"",
			"telescope":{
				"id":"1",
				"name":"P48"
			}
		},
		{
			"exptime":"30",
			"filters":{
				"id":"110",
				"name":"g"
			},
			"flux":"18.69",
			"flux_unit":{
				"id":"1",
				"name":"ABMag"
			},
			"fluxerr":null,
			"instrument":{
				"id":"196",
				"name":"ZTF-Cam"
			},
			"jd":2458426.7169907,
			"limflux":null,
			"obsdate":"2018-11-04 05:12:28",
			"observer":"ZTF",
			"remarks":"",
			"telescope":{
				"id":"1",
				"name":"P48"
			}
		},
		{
			"exptime":"30",
			"filters":{
				"id":"110",
				"name":"g"
			},
			"flux":"18.47",
			"flux_unit":{
				"id":"1",
				"name":"ABMag"
			},
			"fluxerr":null,
			"instrument":{
				"id":"196",
				"name":"ZTF-Cam"
			},
			"jd":2458423.7459954,
			"limflux":null,
			"obsdate":"2018-11-01 05:54:14",
			"observer":"ZTF",
			"remarks":"",
			"telescope":{
				"id":"1",
				"name":"P48"
			}
		},
		{
			"exptime":"30",
			"filters":{
				"id":"110",
				"name":"g"
			},
			"flux":null,
			"flux_unit":{
				"id":"1",
				"name":"ABMag"
			},
			"fluxerr":null,
			"instrument":{
				"id":"196",
				"name":"ZTF-Cam"
			},
			"jd":2458400.775,
			"limflux":"21.03",
			"obsdate":"2018-10-09 06:36:00",
			"observer":"ZTF",
			"remarks":"[Last non detection] ",
			"telescope":{
				"id":"1",
				"name":"P48"
			}
		},
		{
			"exptime":"30",
			"filters":{
				"id":"110",
				"name":"g"
			},
			"flux":null,
			"flux_unit":{
				"id":"1",
				"name":"ABMag"
			},
			"fluxerr":null,
			"instrument":{
				"id":"196",
				"name":"ZTF-Cam"
			},
			"jd":2458400.7749,
			"limflux":"21.03",
			"obsdate":"2018-10-09 06:35:51",
			"observer":null,
			"remarks":"[Last non detection] ",
			"telescope":{
				"id":"1",
				"name":"P48"
			}
		},
		{
			"exptime":"30",
			"filters":{
				"id":"111",
				"name":"r"
			},
			"flux":"18.6425",
			"flux_unit":{
				"id":"1",
				"name":"ABMag"
			},
			"fluxerr":"0.106896",
			"instrument":{
				"id":"196",
				"name":"ZTF-Cam"
			},
			"jd":2458441.7781019,
			"limflux":"19.5809",
			"obsdate":"2018-11-19 06:40:27",
			"observer":null,
			"remarks":"",
			"telescope":{
				"id":"1",
				"name":"P48"
			}
		},
		{
			"exptime":"30",
			"filters":{
				"id":"111",
				"name":"r"
			},
			"flux":"18.4861",
			"flux_unit":{
				"id":"1",
				"name":"ABMag"
			},
			"fluxerr":"0.0980559",
			"instrument":{
				"id":"196",
				"name":"ZTF-Cam"
			},
			"jd":2458435.7598958,
			"limflux":"19.8645",
			"obsdate":"2018-11-13 06:14:15",
			"observer":null,
			"remarks":"",
			"telescope":{
				"id":"1",
				"name":"P48"
			}
		}
	],
	"public":"1",
	"ra":"23:37:12.100",
	"redshift":"0.011",
	"source_group":{
		"group_name":"ATLAS",
		"groupid":"18"
	},
	"sourceid":"2",
	"type":"14"
}