{
	"dec":"+49:48:34.79",
	"discmagfilter":{
		"family":"ZTF",
		"id":"110",
		"name":"g"
	},
	"discoverer":null,
	"discovererid":"49023",
	"discoverydate":"2018-10-06 11:23:47",
	"discoverymag":"17.9772",
	"end_prop_period":null,
	"host_redshift":null,
	"hostname":null,
	"internal_name":"ZTF18aabilqu",
	"isTNS_AT":"1",
	"name":"2018ief",
	"name_prefix":"AT",
	"object_type":{
		"id":null,
		"name":null
	},
	"objname":"2018ief",
	"photometry":[
		{
			"exptime":"30",
			"filters":{
				"id":"110",
				"name":"g"
			},
			"flux":"17.7386",
			"flux_unit":{
				"id":"1",
				"name":"ABMag"
			},
			"fluxerr":"0.0758109",
			"instrument":{
				"id":"196",
				"name":"ZTF-Cam"
			},
			"jd":2458431.9461458,
			"limflux":"20.0033",
			"obsdate":"2018-11-09 10:42:27",
			"observer":null,
			"remarks":"",
			"telescope":{
				"id":"1",
				"name":"P48"
			}
		},
		{
			"exptime":"30",
			"filters":{
				"id":"110",
				"name":"g"
			},
			"flux":"17.9772",
			"flux_unit":{
				"id":"1",
				"name":"ABMag"
			},
			"fluxerr":"0.0743712",
			"instrument":{
				"id":"196",
				"name":"ZTF-Cam"
			},
			"jd":2458429.0280787,
			"limflux":"20.8264",
			"obsdate":"2018-11-06 12:40:26",
			"observer":null,
			"remarks":"",
			"telescope":{
				"id":"1",
				"name":"P48"
			}
		},
		{
			"exptime":"30",
			"filters":{
				"id":"110",
				"name":"g"
			},
			"flux":"17.9397",
			"flux_unit":{
				"id":"1",
				"name":"ABMag"
			},
			"fluxerr":"0.0931137",
			"instrument":{
				"id":"196",
				"name":"ZTF-Cam"
			},
			"jd":2458427.8867245,
			"limflux":"19.1827",
			"obsdate":"2018-11-05 09:16:52",
			"observer":null,
			"remarks":"",
			"telescope":{
				"id":"1",
				"name":"P48"
			}
		},
		{
			"exptime":"30",
			"filters":{
				"id":"110",
				"name":"g"
			},
			"flux":"17.0562",
			"flux_unit":{
				"id":"1",
				"name":"ABMag"
			},
			"fluxerr":"0.110272",
			"instrument":{
				"id":"196",
				"name":"ZTF-Cam"
			},
			"jd":2458427.8657986,
			"limflux":"19.5958",
			"obsdate":"2018-11-05 08:46:45",
			"observer":null,
			"remarks":"",
			"telescope":{
				"id":"1",
				"name":"P48"
			}
		},
		{
			"exptime":"30",
			"filters":{
				"id":"111",
				"name":"r"
			},
			"flux":"16.0738",
			"flux_unit":{
				"id":"1",
				"name":"ABMag"
			},
			"fluxerr":"0.049561",
			"instrument":{
				"id":"196",
				"name":"ZTF-Cam"
			},
			"jd":2458432.0096528,
			"limflux":"19.8831",
			"obsdate":"2018-11-09 12:13:53",
			"observer":null,
			"remarks":"",
			"telescope":{
				"id":"1",
				"name":"P48"
			}
		},
		{
			"exptime":"30",
			"filters":{
				"id":"111",
				"name":"r"
			},
			"flux":"16.5376",
			"flux_unit":{
				"id":"1",
				"name":"ABMag"
			},
			"fluxerr":"0.0389508",
			"instrument":{
				"id":"196",
				"name":"ZTF-Cam"
			},
			"jd":2458432.007338,
			"limflux":"19.919",
			"obsdate":"2018-11-09 12:10:34",
			"observer":null,
			"remarks":"",
			"telescope":{
				"id":"1",
				"name":"P48"
			}
		},
		{
			"exptime":"30",
			"filters":{
				"id":"111",
				"name":"r"
			},
			"flux":"15.9563",
			"flux_unit":{
				"id":"1",
				"name":"ABMag"
			},
			"fluxerr":"0.0470019",
			"instrument":{
				"id":"196",
				"name":"ZTF-Cam"
			},
			"jd":2458428.9988194,
			"limflux":"20.5425",
			"obsdate":"2018-11-06 11:58:18",
			"observer":null,
			"remarks":"",
			"telescope":{
				"id":"1",
				"name":"P48"
			}
		},
		{
			"exptime":"30",
			"filters":{
				"id":"111",
				"name":"r"
			},
			"flux":"16.3805",
			"flux_unit":{
				"id":"1",
				"name":"ABMag"
			},
			"fluxerr":"0.0468543",
			"instrument":{
				"id":"196",
				"name":"ZTF-Cam"
			},
			"jd":2458423.0100579,
			"limflux":"20.0557",
			"obsdate":"2018-10-31 12:14:29",
			"observer":null,
			"remarks":"",
			"telescope":{
				"id":"1",
				"name":"P48"
			}
		}
	],
	"public":"1",
	"ra":"07:42:32.84",
	"redshift":null,
	"source_group":{
		"group_name":"ZTF",
		"groupid":"48"
	},
	"sourceid":"2",
	"type":null
}