{
	"dec":"+17:34:47.23",
	"discmagfilter":{
		"family":"PS1",
		"id":"26",
		"name":"w"
	},
	"discoverer":null,
	"discovererid":"35588",
	"discoverydate":"2018-12-14 13:23:31",
	"discoverymag":"21.05",
	"end_prop_period":null,
	"host_redshift":null,
	"hostname":null,
	"internal_name":"PS18cbk",
	"isTNS_AT":"1",
	"name":"2018jxy",
	"name_prefix":"AT",
	"object_type":{
		"id":null,
		"name":null
	},
	"objname":"2018jxy",
	"photometry":[
		{
			"exptime":"45",
			"filters":{
				"id":"26",
				"name":"w"
			},
			"flux":"21.05",
			"flux_unit":{
				"id":"1",
				"name":"ABMag"
			},
			"fluxerr":"0.15",
			"instrument":{
				"id":"155",
				"name":"GPC1"
			},
			"jd":2458467.0579977,
			"limflux":"22",
			"obsdate":"2018-12-14 13:23:31",
			"observer":"Robot",
			"remarks":"",
			"telescope":{
				"id":"98",
				"name":"PS1"
			}
		},
		{
			"exptime":"30",
			"filters":{
				"id":"72",
				"name":"orange"
			},
			"flux":"19.375",
			"flux_unit":{
				"id":"1",
				"name":"ABMag"
			},
			"fluxerr":"0.155",
			"instrument":{
				"id":"159",
				"name":"ACAM1"
			},
			"jd":2458483.98,
			"limflux":"19.63",
			"obsdate":"2018-12-31 11:31:12",
			"observer":"Robot",
			"remarks":"",
			"telescope":{
				"id":"103",
				"name":"ATLAS1"
			}
		},
		{
			"exptime":"30",
			"filters":{
				"id":"72",
				"name":"orange"
			},
			"flux":null,
			"flux_unit":{
				"id":"1",
				"name":"ABMag"
			},
			"fluxerr":null,
			"instrument":{
				"id":"159",
				"name":"ACAM1"
			},
			"jd":2458482.0159954,
			"limflux":"17.33",
			"obsdate":"2018-12-29 12:23:02",
			"observer":"Robot",
			"remarks":"[Last non detection] ",
			"telescope":{
				"id":"103",
				"name":"ATLAS1"
			}
		},
		{
			"exptime":"30",
			"filters":{
				"id":"111",
				"name":"r"
			},
			"flux":"19.45",
			"flux_unit":{
				"id":"1",
				"name":"ABMag"
			},
			"fluxerr":"0.17",
			"instrument":{
				"id":"196",
				"name":"ZTF-Cam"
			},
			"jd":2458480.9360764,
			"limflux":"19.76",
			"obsdate":"2018-12-28 10:27:57",
			"observer":null,
			"remarks":"",
			"telescope":{
				"id":"1",
				"name":"P48"
			}
		},
		{
			"exptime":"30",
			"filters":{
				"id":"111",
				"name":"r"
			},
			"flux":"19.45",
			"flux_unit":{
				"id":"1",
				"name":"ABMag"
			},
			"fluxerr":"0.17",
			"instrument":{
				"id":"196",
				"name":"ZTF-Cam"
			},
			"jd":2458480.9360764,
			"limflux":"19.76",
			"obsdate":"2018-12-28 10:27:57",
			"observer":null,
			"remarks":"",
			"telescope":{
				"id":"1",
				"name":"P48"
			}
		},
		{
			"exptime":"30",
			"filters":{
				"id":"111",
				"name":"r"
			},
			"flux":"19.41",
			"flux_unit":{
				"id":"1",
				"name":"ABMag"
			},
			"fluxerr":"0.21",
			"instrument":{
				"id":"196",
				"name":"ZTF-Cam"
			},
			"jd":2458480.9239468,
			"limflux":"19.96",
			"obsdate":"2018-12-28 10:10:29",
			"observer":null,
			"remarks":"",
			"telescope":{
				"id":"1",
				"name":"P48"
			}
		},
		{
			"exptime":"30",
			"filters":{
				"id":"111",
				"name":"r"
			},
			"flux":"19.41",
			"flux_unit":{
				"id":"1",
				"name":"ABMag"
			},
			"fluxerr":"0.21",
			"instrument":{
				"id":"196",
				"name":"ZTF-Cam"
			},
			"jd":2458480.9239468,
			"limflux":"19.96",
			"obsdate":"2018-12-28 10:10:29",
			"observer":null,
			"remarks":"",
			"telescope":{
				"id":"1",
				"name":"P48"
			}
		},
		{
			"exptime":"30",
			"filters":{
				"id":"111",
				"name":"r"
			},
			"flux":null,
			"flux_unit":{
				"id":"1",
				"name":"ABMag"
			},
			"fluxerr":null,
			"instrument":{
				"id":"196",
				"name":"ZTF-Cam"
			},
			"jd":2458465.8914,
			"limflux":"20.11",
			"obsdate":"2018-12-13 09:23:36",
			"observer":null,
			"remarks":"[Last non detection] ",
			"telescope":{
				"id":"1",
				"name":"P48"
			}
		},
		{
			"exptime":"30",
			"filters":{
				"id":"111",
				"name":"r"
			},
			"flux":null,
			"flux_unit":{
				"id":"1",
				"name":"ABMag"
			},
			"fluxerr":null,
			"instrument":{
				"id":"196",
				"name":"ZTF-Cam"
			},
			"jd":2458465.8914,
			"limflux":"20.11",
			"obsdate":"2018-12-13 09:23:36",
			"observer":null,
			"remarks":"[Last non detection] ",
			"telescope":{
				"id":"1",
				"name":"P48"
			}
		}
	],
	"public":"1",
	"ra":"07:34:12.449",
	"redshift":null,
	"source_group":{
		"group_name":"Pan-STARRS1",
		"groupid":"4"
	},
	"sourceid":"2",
	"type":null
}