{
	"dec":"-08:11:21.73",
	"decdeg":-8.18936932508,
	"discmagfilter":{
		"family":"ZTF",
		"id":111,
		"name":"r"
	},
	"discoverer":null,
	"discovererid":66140,
	"discoverydate":"2019-08-20 10:03:28",
	"discoverymag":17.475,
	"end_prop_period":null,
	"host_redshift":null,
	"hostname":"HIPASS J0015-08",
	"internal_name":"ZTF19abqrhvt",
	"isTNS_AT":1,
	"name":"2019nyk",
	"name_prefix":"SN",
	"object_type":{
		"id":10,
		"name":"SN II"
	},
	"objname":"2019nyk",
	"photometry":[
		{
			"exptime":45,
			"filters":{
				"id":26,
				"name":"w"
			},
			"flux":17.09,
			"flux_unit":{
				"id":1,
				"name":"ABMag"
			},
			"fluxerr":0.01,
			"instrument":{
				"id":155,
				"name":"GPC1"
			},
			"jd":2458721.9609954,
			"limflux":22,
			"obsdate":"2019-08-26 11:03:50",
			"observer":"Robot",
			"remarks":"",
			"telescope":{
				"id":98,
				"name":"PS1"
			}
		},
		{
			"exptime":30,
			"filters":{
				"id":71,
				"name":"cyan"
			},
			"flux":null,
			"flux_unit":{
				"id":1,
				"name":"ABMag"
			},
			"fluxerr":null,
			"instrument":{
				"id":159,
				"name":"ACAM1"
			},
			"jd":2458709.9539931,
			"limflux":14.69,
			"obsdate":"2019-08-14 10:53:45",
			"observer":"Robot",
			"remarks":"[Last non detection] ",
			"telescope":{
				"id":103,
				"name":"ATLAS1"
			}
		},
		{
			"exptime":30,
			"filters":{
				"id":72,
				"name":"orange"
			},
			"flux":17.107,
			"flux_unit":{
				"id":1,
				"name":"ABMag"
			},
			"fluxerr":0.026,
			"instrument":{
				"id":159,
				"name":"ACAM1"
			},
			"jd":2458718.9839931,
			"limflux":19.48,
			"obsdate":"2019-08-23 11:36:57",
			"observer":"Robot",
			"remarks":"",
			"telescope":{
				"id":103,
				"name":"ATLAS1"
			}
		},
		{
			"exptime":30,
			"filters":{
				"id":110,
				"name":"g"
			},
			"flux":17.0139,
			"flux_unit":{
				"id":1,
				"name":"ABMag"
			},
			"fluxerr":0.0515817,
			"instrument":{
				"id":196,
				"name":"ZTF-Cam"
			},
			"jd":2458716.0026389,
			"limflux":18.8914,
			"obsdate":"2019-08-20 12:03:48",
			"observer":"Robot",
			"remarks":"Data provided by ZTF",
			"telescope":{
				"id":1,
				"name":"P48"
			}
		},
		{
			"exptime":30,
			"filters":{
				"id":111,
				"name":"r"
			},
			"flux":17.475,
			"flux_unit":{
				"id":1,
				"name":"ABMag"
			},
			"fluxerr":0.0396905,
			"instrument":{
				"id":196,
				"name":"ZTF-Cam"
			},
			"jd":2458715.9190741,
			"limflux":19.535,
			"obsdate":"2019-08-20 10:03:28",
			"observer":"Robot",
			"remarks":"Data provided by ZTF",
			"telescope":{
				"id":1,
				"name":"P48"
			}
		},
		{
			"exptime":30,
			"filters":{
				"id":111,
				"name":"r"
			},
			"flux":null,
			"flux_unit":{
				"id":1,
				"name":"ABMag"
			},
			"fluxerr":null,
			"instrument":{
				"id":196,
				"name":"ZTF-Cam"
			},
			"jd":2458710.9214815,
			"limflux":19.4752,
			"obsdate":"2019-08-15 10:06:56",
			"observer":"Robot",
			"remarks":"[Last non detection] Data provided by ZTF",
			"telescope":{
				"id":1,
				"name":"P48"
			}
		}
	],
	"public":1,
	"ra":"00:15:15.197",
	"radeg":3.81332074347,
	"redshift":0.021048,
	"source_group":{
		"group_name":"ALeRCE",
		"groupid":74
	},
	"sourceid":2,
	"type":10
}