{
	"dec":"+07:12:09.63",
	"decdeg":7.2026738,
	"discmagfilter":{
		"family":"ZTF",
		"id":110,
		"name":"g"
	},
	"discoverer":null,
	"discovererid":48869,
	"discoverydate":"2019-06-21 11:05:16",
	"discoverymag":18.84,
	"end_prop_period":null,
	"host_redshift":null,
	"hostname":null,
	"internal_name":"ZTF19abajuqh",
	"isTNS_AT":1,
	"name":"2019ibd",
	"name_prefix":"AT",
	"object_type":{
		"id":null,
		"name":null
	},
	"objname":"2019ibd",
	"photometry":[
		{
			"exptime":30,
			"filters":{
				"id":72,
				"name":"orange"
			},
			"flux":18.156,
			"flux_unit":{
				"id":1,
				"name":"ABMag"
			},
			"fluxerr":0.064,
			"instrument":{
				"id":159,
				"name":"ACAM1"
			},
			"jd":2458661.0589931,
			"limflux":19.35,
			"obsdate":"2019-06-26 13:24:57",
			"observer":"Robot",
			"remarks":"",
			"telescope":{
				"id":103,
				"name":"ATLAS1"
			}
		},
		{
			"exptime":30,
			"filters":{
				"id":72,
				"name":"orange"
			},
			"flux":null,
			"flux_unit":{
				"id":1,
				"name":"ABMag"
			},
			"fluxerr":null,
			"instrument":{
				"id":159,
				"name":"ACAM1"
			},
			"jd":2458655.0839931,
			"limflux":18.97,
			"obsdate":"2019-06-20 14:00:57",
			"observer":"Robot",
			"remarks":"[Last non detection] ",
			"telescope":{
				"id":103,
				"name":"ATLAS1"
			}
		},
		{
			"exptime":30,
			"filters":{
				"id":110,
				"name":"g"
			},
			"flux":18.31,
			"flux_unit":{
				"id":1,
				"name":"ABMag"
			},
			"fluxerr":null,
			"instrument":{
				"id":196,
				"name":"ZTF-Cam"
			},
			"jd":2458658.96,
			"limflux":null,
			"obsdate":"2019-06-24 11:02:24",
			"observer":"ZTF",
			"remarks":"",
			"telescope":{
				"id":1,
				"name":"P48"
			}
		},
		{
			"exptime":30,
			"filters":{
				"id":110,
				"name":"g"
			},
			"flux":18.84,
			"flux_unit":{
				"id":1,
				"name":"ABMag"
			},
			"fluxerr":null,
			"instrument":{
				"id":196,
				"name":"ZTF-Cam"
			},
			"jd":2458655.9619907,
			"limflux":null,
			"obsdate":"2019-06-21 11:05:16",
			"observer":"ZTF",
			"remarks":"",
			"telescope":{
				"id":1,
				"name":"P48"
			}
		},
		{
			"exptime":30,
			"filters":{
				"id":111,
				"name":"r"
			},
			"flux":null,
			"flux_unit":{
				"id":1,
				"name":"ABMag"
			},
			"fluxerr":null,
			"instrument":{
				"id":196,
				"name":"ZTF-Cam"
			},
			"jd":2458652.94,
			"limflux":19.53,
			"obsdate":"2019-06-18 10:33:36",
			"observer":"ZTF",
			"remarks":"[Last non detection] ",
			"telescope":{
				"id":1,
				"name":"P48"
			}
		}
	],
	"public":1,
	"ra":"21:41:46.208",
	"radeg":325.442533,
	"redshift":null,
	"source_group":{
		"group_name":"ZTF",
		"groupid":48
	},
	"sourceid":2,
	"type":null
}