{
	"dec":"+64:23:00.71",
	"decdeg":64.3835317647,
	"discmagfilter":{
		"family":"ATLAS",
		"id":72,
		"name":"orange"
	},
	"discoverer":null,
	"discovererid":35595,
	"discoverydate":"2019-05-27 08:26:52",
	"discoverymag":18.554,
	"end_prop_period":null,
	"host_redshift":null,
	"hostname":null,
	"internal_name":"ATLAS19lsw",
	"isTNS_AT":1,
	"name":"2019gaj",
	"name_prefix":"SN",
	"object_type":{
		"id":3,
		"name":"SN Ia"
	},
	"objname":"2019gaj",
	"photometry":[
		{
			"exptime":30,
			"filters":{
				"id":72,
				"name":"orange"
			},
			"flux":18.554,
			"flux_unit":{
				"id":1,
				"name":"ABMag"
			},
			"fluxerr":0.112,
			"instrument":{
				"id":159,
				"name":"ACAM1"
			},
			"jd":2458630.8519907,
			"limflux":19.35,
			"obsdate":"2019-05-27 08:26:52",
			"observer":"Robot",
			"remarks":"",
			"telescope":{
				"id":103,
				"name":"ATLAS1"
			}
		},
		{
			"exptime":30,
			"filters":{
				"id":72,
				"name":"orange"
			},
			"flux":null,
			"flux_unit":{
				"id":1,
				"name":"ABMag"
			},
			"fluxerr":null,
			"instrument":{
				"id":159,
				"name":"ACAM1"
			},
			"jd":2458626.9129977,
			"limflux":19.05,
			"obsdate":"2019-05-23 09:54:43",
			"observer":"Robot",
			"remarks":"[Last non detection] ",
			"telescope":{
				"id":103,
				"name":"ATLAS1"
			}
		},
		{
			"exptime":30,
			"filters":{
				"id":110,
				"name":"g"
			},
			"flux":19.1,
			"flux_unit":{
				"id":1,
				"name":"ABMag"
			},
			"fluxerr":null,
			"instrument":{
				"id":196,
				"name":"ZTF-Cam"
			},
			"jd":2458628.7069907,
			"limflux":null,
			"obsdate":"2019-05-25 04:58:04",
			"observer":"ZTF",
			"remarks":"",
			"telescope":{
				"id":1,
				"name":"P48"
			}
		},
		{
			"exptime":30,
			"filters":{
				"id":110,
				"name":"g"
			},
			"flux":null,
			"flux_unit":{
				"id":1,
				"name":"ABMag"
			},
			"fluxerr":null,
			"instrument":{
				"id":196,
				"name":"ZTF-Cam"
			},
			"jd":2458619.76,
			"limflux":19.28,
			"obsdate":"2019-05-16 06:14:24",
			"observer":"ZTF",
			"remarks":"[Last non detection] ",
			"telescope":{
				"id":1,
				"name":"P48"
			}
		},
		{
			"exptime":30,
			"filters":{
				"id":111,
				"name":"r"
			},
			"flux":17.73,
			"flux_unit":{
				"id":1,
				"name":"ABMag"
			},
			"fluxerr":null,
			"instrument":{
				"id":196,
				"name":"ZTF-Cam"
			},
			"jd":2458633.8079977,
			"limflux":null,
			"obsdate":"2019-05-30 07:23:31",
			"observer":"ZTF",
			"remarks":"",
			"telescope":{
				"id":1,
				"name":"P48"
			}
		}
	],
	"public":1,
	"ra":"14:12:24.795",
	"radeg":213.103313529,
	"redshift":0.031,
	"source_group":{
		"group_name":"ATLAS",
		"groupid":18
	},
	"sourceid":2,
	"type":3
}