{
	"dec":"+14:16:57.49",
	"decdeg":14.282635375,
	"discmagfilter":{
		"family":"ZTF",
		"id":110,
		"name":"g"
	},
	"discoverer":null,
	"discovererid":49023,
	"discovery_data_source":{
		"group_name":"ZTF",
		"groupid":48
	},
	"discoverydate":"2020-06-05 05:27:06.624",
	"discoverymag":18.14,
	"end_prop_period":null,
	"host_redshift":null,
	"hostname":null,
	"internal_name":"ZTF20abdzrxo",
	"internal_names":"ZTF20abdzrxo, ATLAS20oue",
	"isTNS_AT":1,
	"name":"2020lsc",
	"name_prefix":"SN",
	"object_type":{
		"id":3,
		"name":"SN Ia"
	},
	"objname":"2020lsc",
	"photometry":[
		{
			"exptime":30,
			"filters":{
				"id":72,
				"name":"orange"
			},
			"flux":17.744,
			"flux_unit":{
				"id":1,
				"name":"ABMag"
			},
			"fluxerr":0.095,
			"instrument":{
				"id":159,
				"name":"ACAM1"
			},
			"jd":2459006.919,
			"limflux":18.67,
			"obsdate":"2020-06-06 10:03:22",
			"observer":"Robot",
			"remarks":"",
			"telescope":{
				"id":103,
				"name":"ATLAS1"
			}
		},
		{
			"exptime":30,
			"filters":{
				"id":72,
				"name":"orange"
			},
			"flux":null,
			"flux_unit":{
				"id":1,
				"name":"ABMag"
			},
			"fluxerr":null,
			"instrument":{
				"id":159,
				"name":"ACAM1"
			},
			"jd":2459003.936,
			"limflux":18.94,
			"obsdate":"2020-06-03 10:27:50",
			"observer":"Robot",
			"remarks":"[Last non detection] ",
			"telescope":{
				"id":103,
				"name":"ATLAS1"
			}
		},
		{
			"exptime":30,
			"filters":{
				"id":110,
				"name":"g"
			},
			"flux":18.14,
			"flux_unit":{
				"id":1,
				"name":"ABMag"
			},
			"fluxerr":0.08,
			"instrument":{
				"id":196,
				"name":"ZTF-Cam"
			},
			"jd":2459005.7271644,
			"limflux":19.24,
			"obsdate":"2020-06-05 05:27:07",
			"observer":null,
			"remarks":"",
			"telescope":{
				"id":1,
				"name":"P48"
			}
		},
		{
			"exptime":30,
			"filters":{
				"id":110,
				"name":"g"
			},
			"flux":18.14,
			"flux_unit":{
				"id":1,
				"name":"ABMag"
			},
			"fluxerr":0.08,
			"instrument":{
				"id":196,
				"name":"ZTF-Cam"
			},
			"jd":2459005.7271644,
			"limflux":19.24,
			"obsdate":"2020-06-05 05:27:07",
			"observer":null,
			"remarks":"",
			"telescope":{
				"id":1,
				"name":"P48"
			}
		},
		{
			"exptime":30,
			"filters":{
				"id":110,
				"name":"g"
			},
			"flux":null,
			"flux_unit":{
				"id":1,
				"name":"ABMag"
			},
			"fluxerr":null,
			"instrument":{
				"id":196,
				"name":"ZTF-Cam"
			},
			"jd":2459000.8988426,
			"limflux":20.1966,
			"obsdate":"2020-05-31 09:34:20",
			"observer":null,
			"remarks":"[Last non detection] ",
			"telescope":{
				"id":1,
				"name":"P48"
			}
		},
		{
			"exptime":30,
			"filters":{
				"id":110,
				"name":"g"
			},
			"flux":null,
			"flux_unit":{
				"id":1,
				"name":"ABMag"
			},
			"fluxerr":null,
			"instrument":{
				"id":196,
				"name":"ZTF-Cam"
			},
			"jd":2459000.8988426,
			"limflux":20.1966,
			"obsdate":"2020-05-31 09:34:20",
			"observer":null,
			"remarks":"[Last non detection] ",
			"telescope":{
				"id":1,
				"name":"P48"
			}
		},
		{
			"exptime":30,
			"filters":{
				"id":111,
				"name":"r"
			},
			"flux":18.03,
			"flux_unit":{
				"id":1,
				"name":"ABMag"
			},
			"fluxerr":0.09,
			"instrument":{
				"id":196,
				"name":"ZTF-Cam"
			},
			"jd":2459005.7740741,
			"limflux":19.48,
			"obsdate":"2020-06-05 06:34:40",
			"observer":null,
			"remarks":"",
			"telescope":{
				"id":1,
				"name":"P48"
			}
		},
		{
			"exptime":30,
			"filters":{
				"id":111,
				"name":"r"
			},
			"flux":18.03,
			"flux_unit":{
				"id":1,
				"name":"ABMag"
			},
			"fluxerr":0.09,
			"instrument":{
				"id":196,
				"name":"ZTF-Cam"
			},
			"jd":2459005.7740741,
			"limflux":19.48,
			"obsdate":"2020-06-05 06:34:40",
			"observer":null,
			"remarks":"",
			"telescope":{
				"id":1,
				"name":"P48"
			}
		}
	],
	"public":1,
	"ra":"16:14:03.753",
	"radeg":243.51563905,
	"redshift":0.037,
	"reporting_group":{
		"group_name":"ZTF",
		"groupid":48
	},
	"sourceid":2,
	"type":3
}