{
	"dec":"-31:46:13.79",
	"decdeg":-31.770496875,
	"discmagfilter":{
		"family":"ATLAS",
		"id":71,
		"name":"cyan"
	},
	"discoverer":null,
	"discovererid":35595,
	"discovery_data_source":{
		"group_name":"ATLAS",
		"groupid":18
	},
	"discoverydate":"2020-06-16 06:12:57.600",
	"discoverymag":16.679,
	"end_prop_period":null,
	"host_redshift":null,
	"hostname":null,
	"internal_name":"ATLAS20pmb",
	"internal_names":"ATLAS20pmb",
	"isTNS_AT":1,
	"name":"2020mtk",
	"name_prefix":"AT",
	"object_type":{
		"id":null,
		"name":null
	},
	"objname":"2020mtk",
	"photometry":[
		{
			"exptime":30,
			"filters":{
				"id":71,
				"name":"cyan"
			},
			"flux":16.679,
			"flux_unit":{
				"id":1,
				"name":"ABMag"
			},
			"fluxerr":0.032,
			"instrument":{
				"id":159,
				"name":"ACAM1"
			},
			"jd":2459016.759,
			"limflux":19.24,
			"obsdate":"2020-06-16 06:12:58",
			"observer":"Robot",
			"remarks":"",
			"telescope":{
				"id":103,
				"name":"ATLAS1"
			}
		},
		{
			"exptime":30,
			"filters":{
				"id":72,
				"name":"orange"
			},
			"flux":null,
			"flux_unit":{
				"id":1,
				"name":"ABMag"
			},
			"fluxerr":null,
			"instrument":{
				"id":159,
				"name":"ACAM1"
			},
			"jd":2459015.78,
			"limflux":19.38,
			"obsdate":"2020-06-15 06:43:12",
			"observer":"Robot",
			"remarks":"[Last non detection] ",
			"telescope":{
				"id":103,
				"name":"ATLAS1"
			}
		}
	],
	"public":1,
	"ra":"12:05:47.654",
	"radeg":181.4485575,
	"redshift":null,
	"reporting_group":{
		"group_name":"ATLAS",
		"groupid":18
	},
	"sourceid":2,
	"type":null
}