{
	"dec":"+39:05:40.58",
	"decdeg":39.0946052,
	"discmagfilter":{
		"family":"ZTF",
		"id":110,
		"name":"g"
	},
	"discoverer":null,
	"discovererid":49023,
	"discovery_data_source":{
		"group_name":"ZTF",
		"groupid":48
	},
	"discoverydate":"2020-05-16 03:55:49.728",
	"discoverymag":19.15,
	"end_prop_period":null,
	"host_redshift":null,
	"hostname":null,
	"internal_name":"ZTF20aazquhc",
	"internal_names":"ZTF20aazquhc, ATLAS20mdc",
	"isTNS_AT":1,
	"name":"2020kbh",
	"name_prefix":"SN",
	"object_type":{
		"id":3,
		"name":"SN Ia"
	},
	"objname":"2020kbh",
	"photometry":[
		{
			"exptime":30,
			"filters":{
				"id":71,
				"name":"cyan"
			},
			"flux":18.868,
			"flux_unit":{
				"id":1,
				"name":"ABMag"
			},
			"fluxerr":0.154,
			"instrument":{
				"id":159,
				"name":"ACAM1"
			},
			"jd":2458984.795,
			"limflux":19.76,
			"obsdate":"2020-05-15 07:04:48",
			"observer":"Robot",
			"remarks":"",
			"telescope":{
				"id":103,
				"name":"ATLAS1"
			}
		},
		{
			"exptime":30,
			"filters":{
				"id":72,
				"name":"orange"
			},
			"flux":null,
			"flux_unit":{
				"id":1,
				"name":"ABMag"
			},
			"fluxerr":null,
			"instrument":{
				"id":159,
				"name":"ACAM1"
			},
			"jd":2458982.821,
			"limflux":19.64,
			"obsdate":"2020-05-13 07:42:14",
			"observer":"Robot",
			"remarks":"[Last non detection] ",
			"telescope":{
				"id":103,
				"name":"ATLAS1"
			}
		},
		{
			"exptime":30,
			"filters":{
				"id":110,
				"name":"g"
			},
			"flux":19.09,
			"flux_unit":{
				"id":1,
				"name":"ABMag"
			},
			"fluxerr":0.07,
			"instrument":{
				"id":196,
				"name":"ZTF-Cam"
			},
			"jd":2458985.6760764,
			"limflux":20.81,
			"obsdate":"2020-05-16 04:13:33",
			"observer":null,
			"remarks":"",
			"telescope":{
				"id":1,
				"name":"P48"
			}
		},
		{
			"exptime":30,
			"filters":{
				"id":110,
				"name":"g"
			},
			"flux":19.09,
			"flux_unit":{
				"id":1,
				"name":"ABMag"
			},
			"fluxerr":0.07,
			"instrument":{
				"id":196,
				"name":"ZTF-Cam"
			},
			"jd":2458985.6760764,
			"limflux":20.81,
			"obsdate":"2020-05-16 04:13:33",
			"observer":null,
			"remarks":"",
			"telescope":{
				"id":1,
				"name":"P48"
			}
		},
		{
			"exptime":30,
			"filters":{
				"id":110,
				"name":"g"
			},
			"flux":19.15,
			"flux_unit":{
				"id":1,
				"name":"ABMag"
			},
			"fluxerr":0.09,
			"instrument":{
				"id":196,
				"name":"ZTF-Cam"
			},
			"jd":2458985.6637731,
			"limflux":20.55,
			"obsdate":"2020-05-16 03:55:50",
			"observer":null,
			"remarks":"",
			"telescope":{
				"id":1,
				"name":"P48"
			}
		},
		{
			"exptime":30,
			"filters":{
				"id":110,
				"name":"g"
			},
			"flux":19.15,
			"flux_unit":{
				"id":1,
				"name":"ABMag"
			},
			"fluxerr":0.09,
			"instrument":{
				"id":196,
				"name":"ZTF-Cam"
			},
			"jd":2458985.6637731,
			"limflux":20.55,
			"obsdate":"2020-05-16 03:55:50",
			"observer":null,
			"remarks":"",
			"telescope":{
				"id":1,
				"name":"P48"
			}
		},
		{
			"exptime":30,
			"filters":{
				"id":111,
				"name":"r"
			},
			"flux":null,
			"flux_unit":{
				"id":1,
				"name":"ABMag"
			},
			"fluxerr":null,
			"instrument":{
				"id":196,
				"name":"ZTF-Cam"
			},
			"jd":2458980.7345139,
			"limflux":20.7207,
			"obsdate":"2020-05-11 05:37:42",
			"observer":null,
			"remarks":"[Last non detection] ",
			"telescope":{
				"id":1,
				"name":"P48"
			}
		},
		{
			"exptime":30,
			"filters":{
				"id":111,
				"name":"r"
			},
			"flux":null,
			"flux_unit":{
				"id":1,
				"name":"ABMag"
			},
			"fluxerr":null,
			"instrument":{
				"id":196,
				"name":"ZTF-Cam"
			},
			"jd":2458980.7345139,
			"limflux":20.7207,
			"obsdate":"2020-05-11 05:37:42",
			"observer":null,
			"remarks":"[Last non detection] ",
			"telescope":{
				"id":1,
				"name":"P48"
			}
		}
	],
	"public":1,
	"ra":"10:44:34.999",
	"radeg":161.1458302,
	"redshift":0.03456,
	"reporting_group":{
		"group_name":"ZTF",
		"groupid":48
	},
	"sourceid":2,
	"type":3
}